jsonspot/__init__.py
jsonspot/comDef.py
jsonspot/exceptions.py
jsonspot/jsonspot.py
jsonspot/main.py
jsonspot/test.py
jsonspot-0.0.7.dist-info/METADATA
jsonspot-0.0.7.dist-info/WHEEL
jsonspot-0.0.7.dist-info/top_level.txt
jsonspot-0.0.7.dist-info/RECORD
